Metadata-Version: 2.1
Name: tablelinker-lib
Version: 1.0.0
Summary: A library of processes for manipulating tabular data in CSV format
Home-page: https://github.com/KMCS-NII/tablelinker-lib
Keywords: CSV,tabular,manipulation,cleansing
Author: Akiko Aizawa
Author-email: akiko@nii.ac.jp
Maintainer: Takeshi Sagara
Maintainer-email: sagara@info-proto.com
Requires-Python: >=3.8.1,<3.11.0
Classifier: License :: OSI Approved :: MIT License
Classifier: Operating System :: Microsoft :: Windows :: Windows 11
Classifier: Operating System :: POSIX :: Linux
Classifier: Programming Language :: Python :: 3
Classifier: Programming Language :: Python :: 3.9
Classifier: Programming Language :: Python :: 3.10
Classifier: Programming Language :: Python :: 3
Requires-Dist: charset-normalizer (>=3.0.1,<4.0.0)
Requires-Dist: docopt (>=0.6.2,<0.7.0)
Requires-Dist: fugashi (>=1.2.1,<2.0.0)
Requires-Dist: install (>=1.3.5,<2.0.0)
Requires-Dist: ipadic (>=1.0.0,<2.0.0)
Requires-Dist: jaconv (>=0.3.3,<0.4.0)
Requires-Dist: jageocoder (>=1.4.0,<2.0.0)
Requires-Dist: jeraconv (>=0.2.1,<0.3.0)
Requires-Dist: munkres (>=1.1.4,<2.0.0)
Requires-Dist: openpyxl (>=3.0.10,<4.0.0)
Requires-Dist: pandas (>=1.5.2,<2.0.0)
Requires-Dist: requests (>=2.28.1,<3.0.0)
Requires-Dist: torch (>=1.13.1,<2.0.0)
Requires-Dist: transformers (>=4.25.1,<5.0.0)
Requires-Dist: xlrd (>=2.0.1,<3.0.0)
Project-URL: Documentation, https://www2.info-proto.com/tablelinker/
Project-URL: Repository, https://github.com/KMCS-NII/tablelinker-lib
